{
  "session": {
    "vram_path": "",
    "cgram_path": "",
    "oam_path": "",
    "output_name": "",
    "create_grayscale": true,
    "create_metadata": true,
    "extraction_mode": 0,
    "last_rom_path": "",
    "last_vram_path": "",
    "last_output_dir": "",
    "recent_files": [],
    "data": {
      "vram_path": "",
      "cgram_path": "",
      "oam_path": "",
      "extraction_mode": 0,
      "output_name": "",
      "create_grayscale": true,
      "create_metadata": true
    }
  },
  "ui": {
    "window_width": 1707,
    "window_height": 996,
    "window_x": 0,
    "window_y": -7,
    "restore_position": true,
    "theme": "default"
  },
  "paths": {
    "last_used_dir": "C:\\CustomScripts\\KirbyMax\\workshop\\exhal-master\\spritepal\\roms",
    "default_dumps_dir": "C:\\Users\\gabri\\Documents\\Mesen2\\Debugger",
    "last_export_dir": "",
    "last_import_dir": ""
  },
  "test": {
    "key": "value",
    "data": "value",
    "new_data": "new_value",
    "key1": "value1",
    "adapter_key": "adapter_value"
  },
  "rom_injection": {
    "last_input_rom": "C:/CustomScripts/KirbyMax/workshop/exhal-master/spritepal/roms/Kirby Super Star (U) [!].smc",
    "last_sprite_location": "Kirby Sprite (0x123456)",
    "last_custom_offset": "0x123456",
    "fast_compression": true,
    "last_output_rom": ""
  },
  "extraction": {
    "default_tile_width": 256,
    "auto_detect_size": true,
    "preserve_transparency": true,
    "compression_level": 6,
    "palette_format": "rgb888",
    "include_unused_palettes": false,
    "tile_width": 256
  },
  "appearance": {
    "color_scheme": {
      "theme": "dark",
      "preview_background": "#2b2b2b",
      "grid_color": "#555555",
      "selection_color": "#4a90e2",
      "transparency_pattern": "checkerboard"
    },
    "theme": "dark"
  },
  "cache": {
    "enabled": true,
    "location": "/tmp/pytest-of-gabrielh/pytest-21/test_cache_location_change_dur0/cache/cache2",
    "max_size_mb": 500,
    "expiration_days": 30,
    "auto_cleanup": true,
    "show_indicators": true
  },
  "recent_files": {
    "vram": [],
    "cgram": [],
    "oam": [],
    "rom": [],
    "max_recent": 10
  },
  "manual_offset_dialog": {
    "x": 100,
    "y": 100,
    "width": 800,
    "height": 600
  },
  "experimental": {
    "use_composed_dialogs": true
  }
}